ldappool/__init__.py
ldappool/tests/__init__.py
ldappool/tests/test_ldapconnection.py
ldappool/tests/test_ldappool.py
ldappool-3.0.0.dist-info/AUTHORS
ldappool-3.0.0.dist-info/METADATA
ldappool-3.0.0.dist-info/WHEEL
ldappool-3.0.0.dist-info/pbr.json
ldappool-3.0.0.dist-info/top_level.txt
ldappool-3.0.0.dist-info/RECORD
